{
    "MSH": {
      "MSH_3": "Hospital",
      "MSH_4": "Clinic"
    },
    "PID": {
      "PID_3": "12345",
      "PID_5": "Doe^John",
      "PID_7": "19800101",
      "PID_8": "M",
      "PID_11": "123 Main St",
      "PID_13": "City",
      "PID_14": "State",
      "PID_16": "12345",
      "PID_18": "123-456-7890"
    },
    "PV1": {
      "PV1_2": "O",
      "PV1_3": "Consultation",
      "PV1_8": "20190601",
      "PV1_9": "20190602",
      "PV1_10": "Doctor",
      "PV1_13": "Ward A",
      "PV1_17": "123456"
    }
  }
  